django_qrcodes/__init__.py
django_qrcodes/admin.py
django_qrcodes/apps.py
django_qrcodes/models.py
django_qrcodes/version.py
django_qrcodes/views.py
django_qrcodes/migrations/0001_initial.py
django_qrcodes/migrations/__init__.py
django_qrcodes/static/.gitinclude
django_qrcodes/static/img/qr_logo.png
django_qrcodes/static/qrcodes/img/qr_logo.png
django_qrcodes-0.1.1.dist-info/LICENSE
django_qrcodes-0.1.1.dist-info/METADATA
django_qrcodes-0.1.1.dist-info/WHEEL
django_qrcodes-0.1.1.dist-info/top_level.txt
django_qrcodes-0.1.1.dist-info/RECORD
